galumph/__init__.py
galumph/almarray.py
galumph/atomicscattering.py
galumph/gaunt.py
galumph/intensity.py
galumph/rotalm.py
galumph/sphericalbessel.py
galumph/sphericalharmonic.py
galumph/util.py
galumph/zshift.py
galumph/cl-src/alm-add-atom.cl
galumph/cl-src/intensity.cl
galumph/cl-src/rotate-alm.cl
galumph/cl-src/spherical-bessel.cl
galumph/cl-src/spherical-harmonic.cl
galumph/cl-src/translate-alm.cl
galumph-0.3.0.dist-info/COPYING
galumph-0.3.0.dist-info/METADATA
galumph-0.3.0.dist-info/WHEEL
galumph-0.3.0.dist-info/top_level.txt
galumph-0.3.0.dist-info/RECORD
