Metadata-Version: 2.1
Name: galumph
Version: 0.3.0
Summary: Calculate ALM using GPU acceleration
Home-page: https://git.embl.de/grp-svergun/galumph
Author: Christopher Kerr
Author-email: chris.kerr@mykolab.ch
License: UNKNOWN
Platform: UNKNOWN
Classifier: Development Status :: 3 - Alpha
Classifier: Environment :: Console
Classifier: Intended Audience :: Developers
Classifier: Intended Audience :: Science/Research
Classifier: License :: OSI Approved :: GNU Lesser General Public License v3 or later (LGPLv3+)
Classifier: Natural Language :: English
Classifier: Programming Language :: Python :: 3
Classifier: Programming Language :: Python :: 3.5
Classifier: Programming Language :: Python :: 3.6
Classifier: Programming Language :: Python :: 3.7
Classifier: Programming Language :: Python :: 3.8
Requires: pyopencl
Requires-Python: >=3.5
